tuify/__init__.py
tuify/__main__.py
tuify-0.1.0.post3.dist-info/LICENSE
tuify-0.1.0.post3.dist-info/WHEEL
tuify-0.1.0.post3.dist-info/METADATA
tuify-0.1.0.post3.dist-info/RECORD
