Metadata-Version: 2.1
Name: tuify
Version: 0.1.0.post3
Summary: Transforming Python CLIs into TUIs
Home-page: https://github.com/alwinw/tuify
License: MIT
Author: alwinw
Author-email: 16846521+alwinw@users.noreply.github.com
Requires-Python: >=3.7,<4.0
Classifier: License :: OSI Approved :: MIT License
Classifier: Programming Language :: Python :: 3
Classifier: Programming Language :: Python :: 3.10
Classifier: Programming Language :: Python :: 3.7
Classifier: Programming Language :: Python :: 3.8
Classifier: Programming Language :: Python :: 3.9
Requires-Dist: rich (>=12.0.0,<13.0.0)
Project-URL: Documentation, https://github.com/alwinw/tuify
Project-URL: Repository, https://github.com/alwinw/tuify
